MANIFEST.in
README.rst
VERSION
requirements.txt
setup.py
woocommerce_subscription_check/__init__.py
woocommerce_subscription_check/app.py
woocommerce_subscription_check/config.py
woocommerce_subscription_check/exceptions.py
woocommerce_subscription_check/helpers.py
woocommerce_subscription_check/setup_app.py
woocommerce_subscription_check/woocommerce_calls.py
woocommerce_subscription_check/blueprints/__init__.py
woocommerce_subscription_check/blueprints/healthcheck_endpoints.py
woocommerce_subscription_check/blueprints/login_endpoints.py
woocommerce_subscription_check/blueprints/subscriptions_endpoints.py
woocommerce_subscriptions_check.egg-info/PKG-INFO
woocommerce_subscriptions_check.egg-info/SOURCES.txt
woocommerce_subscriptions_check.egg-info/dependency_links.txt
woocommerce_subscriptions_check.egg-info/entry_points.txt
woocommerce_subscriptions_check.egg-info/requires.txt
woocommerce_subscriptions_check.egg-info/top_level.txt