Metadata-Version: 2.1
Name: woocommerce-subscriptions-check
Version: 1.0.6
Summary: Check user subscriptions in Woocommerce without have and admin role
Home-page: https://github.com/cr0hn/woocommerce-subscriptions-check
Author: Daniel Garcia (cr0hn)
License: UNKNOWN
Platform: UNKNOWN
Classifier: Environment :: Console
Classifier: Intended Audience :: System Administrators
Classifier: Intended Audience :: Other Audience
Classifier: License :: OSI Approved :: BSD License
Classifier: Operating System :: MacOS
Classifier: Operating System :: Microsoft :: Windows
Classifier: Operating System :: POSIX
Classifier: Programming Language :: Python :: 3
Provides-Extra: sentry
